include/fmt/ostream.h
include/fmt/format-inl.h
include/fmt/ranges.h
include/fmt/xchar.h
include/fmt/core.h
include/fmt/chrono.h
include/fmt/os.h
include/fmt/color.h
include/fmt/args.h
include/fmt/printf.h
include/fmt/compile.h
include/fmt/format.h
include/fmt/std.h
include/fmt/base.h
llvmpym-0.0.6.dist-info/RECORD
llvmpym-0.0.6.dist-info/WHEEL
llvmpym-0.0.6.dist-info/METADATA
llvmpym-0.0.6.dist-info/licenses/LICENSE
llvmpym-0.0.6.dist-info/licenses/LICENSE.LLVM
llvmpym/support.py
llvmpym/analysis.py
llvmpym/object.py
llvmpym/disassembler.py
llvmpym/__init__.py
llvmpym/core.py
llvmpym/llvmpym_ext.cpython-311-darwin.so
llvmpym/error_handling.py
llvmpym/utils.py
llvmpym/linker.py
llvmpym/target.py
llvmpym/target_machine.py
llvmpym/bit_reader.py
llvmpym/llvmpym_ext/linker.pyi
llvmpym/llvmpym_ext/object.pyi
llvmpym/llvmpym_ext/__init__.pyi
llvmpym/llvmpym_ext/disassembler.pyi
llvmpym/llvmpym_ext/core.pyi
llvmpym/llvmpym_ext/target_machine.pyi
llvmpym/llvmpym_ext/analysis.pyi
llvmpym/llvmpym_ext/utils.pyi
llvmpym/llvmpym_ext/error_handling.pyi
llvmpym/llvmpym_ext/bit_reader.pyi
llvmpym/llvmpym_ext/support.pyi
llvmpym/llvmpym_ext/target.pyi
llvmpym/.dylibs/libc++abi.1.0.dylib
llvmpym/.dylibs/libunwind.1.0.dylib
llvmpym/.dylibs/libz3.4.13.0.0.dylib
llvmpym/.dylibs/libc++.1.0.dylib
llvmpym/.dylibs/libzstd.1.5.6.dylib
lib/libfmt.a
lib/pkgconfig/fmt.pc
lib/cmake/fmt/fmt-targets-release.cmake
lib/cmake/fmt/fmt-config.cmake
lib/cmake/fmt/fmt-config-version.cmake
lib/cmake/fmt/fmt-targets.cmake
