Metadata-Version: 2.1
Name: llvmpym
Version: 0.0.6
Summary: LLVM python binding
Author-Email: Meow King <mr.meowking@anche.no>
License: MIT License
Classifier: Programming Language :: Python :: 3
Classifier: Programming Language :: Python :: 3.12
Project-URL: Homepage, https://github.com/Ziqi-Yang/llvmpym
Requires-Python: >=3.11
